cachetools/__init__.py
cachetools/func.py
cachetools/keys.py
cachetools/rcache.py
py_redis_cachetools-0.1.2.dist-info/WHEEL
py_redis_cachetools-0.1.2.dist-info/METADATA
py_redis_cachetools-0.1.2.dist-info/RECORD
