Metadata-Version: 2.1
Name: py-redis-cachetools
Version: 0.1.2
Summary: cachetools core + redis
Home-page: https://500apps.com
Keywords: py-redis-cachetools
Author: 500apps
Author-email: satyabrata.swain@500apps.com
Requires-Python: >=3.8,<4.0
Classifier: Operating System :: OS Independent
Classifier: Programming Language :: Python :: 3
Classifier: Programming Language :: Python :: 3.8
Classifier: Programming Language :: Python :: 3.9
Classifier: Programming Language :: Python :: 3.10
Classifier: Topic :: Software Development :: Documentation
Classifier: Topic :: Software Development :: Libraries :: Python Modules
Classifier: Topic :: Software Development :: Quality Assurance
Requires-Dist: redis (>=3.5.3,<4.0.0)
Project-URL: Repository, https://500apps.com
